xstatic/__init__.py
xstatic/pkg/__init__.py
xstatic/pkg/socialshareprivacy/.DS_Store
xstatic/pkg/socialshareprivacy/__init__.py
xstatic/pkg/socialshareprivacy/data/.DS_Store
xstatic/pkg/socialshareprivacy/data/socialshareprivacy/.DS_Store
xstatic/pkg/socialshareprivacy/data/socialshareprivacy/2-klick-logo_min.jpg
xstatic/pkg/socialshareprivacy/data/socialshareprivacy/dimensions.gif
xstatic/pkg/socialshareprivacy/data/socialshareprivacy/index.html
xstatic/pkg/socialshareprivacy/data/socialshareprivacy/jquery.socialshareprivacy.js
xstatic/pkg/socialshareprivacy/data/socialshareprivacy/jquery.socialshareprivacy.min.js
xstatic/pkg/socialshareprivacy/data/socialshareprivacy/socialshareprivacy/.DS_Store
xstatic/pkg/socialshareprivacy/data/socialshareprivacy/socialshareprivacy/socialshareprivacy.css
xstatic/pkg/socialshareprivacy/data/socialshareprivacy/socialshareprivacy/images/.DS_Store
xstatic/pkg/socialshareprivacy/data/socialshareprivacy/socialshareprivacy/images/2-klick-logo.jpg
xstatic/pkg/socialshareprivacy/data/socialshareprivacy/socialshareprivacy/images/dummy_facebook.png
xstatic/pkg/socialshareprivacy/data/socialshareprivacy/socialshareprivacy/images/dummy_facebook_en.png
xstatic/pkg/socialshareprivacy/data/socialshareprivacy/socialshareprivacy/images/dummy_gplus.png
xstatic/pkg/socialshareprivacy/data/socialshareprivacy/socialshareprivacy/images/dummy_gplus_alt.png
xstatic/pkg/socialshareprivacy/data/socialshareprivacy/socialshareprivacy/images/dummy_twitter.png
xstatic/pkg/socialshareprivacy/data/socialshareprivacy/socialshareprivacy/images/settings.png
xstatic/pkg/socialshareprivacy/data/socialshareprivacy/socialshareprivacy/images/socialshareprivacy_info.png
xstatic/pkg/socialshareprivacy/data/socialshareprivacy/socialshareprivacy/images/socialshareprivacy_on_off.png
xstatic_socialshareprivacy-1.4.1.dist-info/METADATA
xstatic_socialshareprivacy-1.4.1.dist-info/WHEEL
xstatic_socialshareprivacy-1.4.1.dist-info/top_level.txt
xstatic_socialshareprivacy-1.4.1.dist-info/RECORD
