Metadata-Version: 2.4
Name: XStatic-socialshareprivacy
Version: 1.4.1
Summary: socialshareprivacy 1.4 (XStatic packaging standard)
Home-page: http://www.heise.de/extras/socialshareprivacy/
Maintainer: Raphael Jasjukaitis
Maintainer-email: webmaster@raphaa.de
License: (same as socialshareprivacy)
Keywords: socialshareprivacy xstatic
Platform: any
Requires-Dist: xstatic
Dynamic: description
Dynamic: home-page
Dynamic: keywords
Dynamic: license
Dynamic: maintainer
Dynamic: maintainer-email
Dynamic: platform
Dynamic: requires-dist
Dynamic: summary
